miblab_dl/__init__.py
miblab_dl/dlseg.py
miblab_dl/dlsegkidney.py
miblab_dl/fatwatermap.py
miblab_dl-0.0.10.dist-info/licenses/LICENSE
miblab_dl-0.0.10.dist-info/METADATA
miblab_dl-0.0.10.dist-info/WHEEL
miblab_dl-0.0.10.dist-info/top_level.txt
miblab_dl-0.0.10.dist-info/RECORD
