Metadata-Version: 2.4
Name: miblab-dl
Version: 0.0.10
Summary: Python API for miblab's trained deep-learning models
Author-email: Steven Sourbron <s.sourbron@sheffield.ac.uk>, Joao Periquito <j.s.periquito@sheffield.ac.uk>
License-Expression: Apache-2.0
Project-URL: Homepage, https://miblab.org/
Project-URL: Source Code, https://github.com/openmiblab/docs-miblab-dl
Keywords: python,medical imaging,MRI,deep learning
Classifier: Development Status :: 3 - Alpha
Classifier: Intended Audience :: Developers
Classifier: Intended Audience :: Science/Research
Classifier: Topic :: Scientific/Engineering
Classifier: Operating System :: OS Independent
Classifier: Programming Language :: Python
Classifier: Programming Language :: Python :: 3
License-File: LICENSE
Requires-Dist: platformdirs
Requires-Dist: numpy
Requires-Dist: nibabel
Requires-Dist: miblab-data
Requires-Dist: nnunetv2
Requires-Dist: vreg
Requires-Dist: TotalSegmentator
Requires-Dist: torch
Requires-Dist: monai==1.3.2
Requires-Dist: scipy
Requires-Dist: tqdm
Dynamic: license-file
